integrify/kapitalbank/__init__.py
integrify/kapitalbank/client.py
integrify/kapitalbank/env.py
integrify/kapitalbank/handlers.py
integrify/kapitalbank/schemas/__init__.py
integrify/kapitalbank/schemas/enums.py
integrify/kapitalbank/schemas/request.py
integrify/kapitalbank/schemas/utils.py
integrify/kapitalbank/schemas/response/__init__.py
integrify/kapitalbank/schemas/response/base_response.py
integrify/kapitalbank/schemas/response/detailed_order_response.py
integrify/kapitalbank/schemas/response/order_response.py
integrify/kapitalbank/schemas/response/refund_response.py
integrify/kapitalbank/schemas/response/token_response.py
integrify_kapitalbank-1.0.0.dist-info/METADATA
integrify_kapitalbank-1.0.0.dist-info/WHEEL
integrify_kapitalbank-1.0.0.dist-info/licenses/LICENSE
integrify_kapitalbank-1.0.0.dist-info/RECORD
