Metadata-Version: 2.3
Name: integrify-kapitalbank
Version: 1.0.0
Summary: Integrify API inteqrasiyalarını rahatlaşdıran sorğular kitabaxanasıdır. Bu kitabxana KapitalBank inteqrasiyası üçün nəzərdə tutulmuşdur.
Project-URL: Homepage, https://integrify.mmzeynalli.dev/integrations/kapitalbank/about
Project-URL: Repository, https://github.com/Integrify-SDK/integrify-kapitalbank-python
Project-URL: Documentation, https://integrify.mmzeynalli.dev/integrations/kapitalbank/about
Author-email: mmzeynalli <miradil.zeynalli@gmail.com>
License: GPL-3.0-or-later
Classifier: Environment :: Web Environment
Classifier: Framework :: AsyncIO
Classifier: Framework :: Pydantic
Classifier: Intended Audience :: Developers
Classifier: Intended Audience :: Information Technology
Classifier: Intended Audience :: System Administrators
Classifier: License :: OSI Approved :: GNU General Public License v3 or later (GPLv3+)
Classifier: Operating System :: OS Independent
Classifier: Programming Language :: Python
Classifier: Programming Language :: Python :: 3
Classifier: Programming Language :: Python :: 3 :: Only
Classifier: Programming Language :: Python :: 3.9
Classifier: Programming Language :: Python :: 3.10
Classifier: Programming Language :: Python :: 3.11
Classifier: Programming Language :: Python :: 3.12
Classifier: Programming Language :: Python :: 3.13
Classifier: Topic :: Internet
Classifier: Topic :: Internet :: WWW/HTTP
Classifier: Topic :: Internet :: WWW/HTTP :: HTTP Servers
Classifier: Topic :: Software Development
Classifier: Topic :: Software Development :: Libraries
Classifier: Topic :: Software Development :: Libraries :: Python Modules
Classifier: Typing :: Typed
Requires-Python: ~=3.9
Requires-Dist: integrify-core<2,>=1.0.3
